speechlight-3.0.0.dist-info/METADATA
speechlight-3.0.0.dist-info/WHEEL
speechlight-3.0.0.dist-info/entry_points.txt
speechlight-3.0.0.dist-info/licenses/LICENSE.txt
speechlight/__init__.py
speechlight/_version.py
speechlight/base.py
speechlight/darwin.py
speechlight/dummy.py
speechlight/py.typed
speechlight/speech_libs/SAAPI32.dll
speechlight/speech_libs/SAAPI64.dll
speechlight/speech_libs/nvdaControllerClient32.dll
speechlight/speech_libs/nvdaControllerClient64.dll
speechlight/windows.py
speechlight-3.0.0.dist-info/RECORD
