Metadata-Version: 2.1
Name: speechlight
Version: 3.0.0
Summary: A lightweight Python library providing a common interface to multiple TTS and screen reader APIs.
Keywords: blind,braille,screen reader,tts,speech,accessibility,jaws,nvda,sapi,system access
Author-Email: Nick Stockton <nstockton@users.noreply.github.com>
License: MIT
Classifier: Development Status :: 5 - Production/Stable
Classifier: Intended Audience :: Developers
Classifier: License :: OSI Approved :: MIT License
Classifier: Programming Language :: Python
Classifier: Programming Language :: Python :: 3
Classifier: Programming Language :: Python :: 3 :: Only
Classifier: Programming Language :: Python :: 3.10
Classifier: Programming Language :: Python :: 3.11
Classifier: Programming Language :: Python :: 3.12
Classifier: Programming Language :: Python :: 3.13
Classifier: Programming Language :: Python :: 3.14
Classifier: Programming Language :: Python :: Implementation
Classifier: Programming Language :: Python :: Implementation :: CPython
Classifier: Operating System :: MacOS
Classifier: Operating System :: MacOS :: MacOS X
Classifier: Operating System :: Microsoft
Classifier: Operating System :: Microsoft :: Windows
Classifier: Operating System :: OS Independent
Classifier: Operating System :: POSIX
Classifier: Operating System :: POSIX :: BSD
Classifier: Operating System :: POSIX :: Linux
Classifier: Operating System :: Unix
Classifier: Topic :: Adaptive Technologies
Classifier: Topic :: Software Development
Classifier: Topic :: Software Development :: Libraries
Classifier: Topic :: Software Development :: Libraries :: Python Modules
Project-URL: homepage, https://github.com/nstockton/speechlight
Project-URL: repository, https://github.com/nstockton/speechlight
Project-URL: documentation, https://nstockton.github.io/speechlight
Requires-Python: <4.0,>=3.10
Requires-Dist: knickknacks<1.0.0,>=0.6.0
Requires-Dist: pyobjc<13.0,>=12.0; sys_platform == "darwin"
Requires-Dist: pywin32<400,>=311; sys_platform == "win32"
